ssqlconnect/__init__.py
ssqlconnect/Data.py
ssqlconnect/logger.py
ssqlconnect/SSQL.py
ssqlconnect-0.1.3.dist-info/METADATA
ssqlconnect-0.1.3.dist-info/WHEEL
ssqlconnect-0.1.3.dist-info/RECORD
