Metadata-Version: 2.1
Name: ssqlconnect
Version: 0.1.3
Summary: Simplify MySQL
Home-page: https://pypi.org/project/ssqlconnect/
License: MIT
Author: BazzoniEdoardo
Author-email: bazzoni.edoardo@gmail.com
Maintainer: bazzoniEdoardo
Maintainer-email: bazzoni.edoardo@gmail.com
Requires-Python: >=3.11,<4.0
Classifier: License :: OSI Approved :: MIT License
Classifier: Programming Language :: Python :: 3
Classifier: Programming Language :: Python :: 3.11
Classifier: Programming Language :: Python :: 3.12
Requires-Dist: mysql-connector-python (>=9.0.0,<10.0.0)
Project-URL: Documentation, https://github.com/BazzoniEdoardo/SSQL/blob/main/README.md
Project-URL: Repository, https://github.com/BazzoniEdoardo/SSQL
